{"id": "lp-panda-boern", "title": "lp-panda", "width": 512, "height": 512, "palette": [{"number": 1, "hex": "#1a1a1a", "name": "Farve 1"}, {"number": 2, "hex": "#fdfdfd", "name": "Farve 2"}, {"number": 3, "hex": "#9a9a9a", "name": "Farve 3"}, {"number": 4, "hex": "#dbdadb", "name": "Farve 4"}, {"number": 5, "hex": "#3a3a3a", "name": "Farve 5"}, {"number": 6, "hex": "#5b5b5b", "name": "Farve 6"}, {"number": 7, "hex": "#7a7a7a", "name": "Farve 7"}, {"number": 8, "hex": "#c5b6bb", "name": "Farve 8"}], "regions": [{"id": "r0", "number": 2, "path": "M31.4 208.9 L76.4 331.3 L0.0 288.0 Z", "centroid": [36.0, 276.1], "size": 60.9}, {"id": "r1", "number": 2, "path": "M0.0 192.0 L31.4 208.9 L0.0 288.0 Z", "centroid": [10.5, 229.6], "size": 38.8}, {"id": "r2", "number": 2, "path": "M76.4 331.3 L0.0 384.0 L0.0 288.0 Z", "centroid": [25.5, 334.4], "size": 60.6}, {"id": "r3", "number": 2, "path": "M0.0 480.0 L96.0 511.0 L0.0 511.0 Z", "centroid": [32.0, 500.7], "size": 38.6}, {"id": "r4", "number": 2, "path": "M81.3 424.1 L0.0 384.0 L76.4 331.3 Z", "centroid": [52.6, 379.8], "size": 60.6}, {"id": "r5", "number": 2, "path": "M81.3 424.1 L0.0 480.0 L0.0 384.0 Z", "centroid": [27.1, 429.4], "size": 62.5}, {"id": "r6", "number": 2, "path": "M0.0 480.0 L81.3 424.1 L96.0 511.0 Z", "centroid": [59.1, 471.7], "size": 62.8}, {"id": "r7", "number": 2, "path": "M96.0 0.0 L64.8 29.4 L0.0 0.0 Z", "centroid": [53.6, 9.8], "size": 37.6}, {"id": "r8", "number": 2, "path": "M64.8 29.4 L0.0 96.0 L0.0 0.0 Z", "centroid": [21.6, 41.8], "size": 55.8}, {"id": "r9", "number": 2, "path": "M164.9 255.5 L170.7 355.7 L76.4 331.3 Z", "centroid": [137.3, 314.2], "size": 68.2}, {"id": "r10", "number": 2, "path": "M164.9 255.5 L76.4 331.3 L31.4 208.9 Z", "centroid": [90.9, 265.2], "size": 84.4}, {"id": "r11", "number": 2, "path": "M257.8 142.8 L164.3 101.4 L249.6 18.2 Z", "centroid": [223.9, 87.5], "size": 75.2}, {"id": "r12", "number": 4, "path": "M164.3 101.4 L257.8 142.8 L177.9 152.4 Z", "centroid": [200.0, 132.2], "size": 45.9}, {"id": "r13", "number": 2, "path": "M511.0 96.0 L460.9 35.4 L511.0 0.0 Z", "centroid": [494.3, 43.8], "size": 49.0}, {"id": "r14", "number": 2, "path": "M511.0 384.0 L460.3 324.3 L511.0 288.0 Z", "centroid": [494.1, 332.1], "size": 49.3}, {"id": "r15", "number": 2, "path": "M339.6 406.0 L384.0 511.0 L288.0 511.0 Z", "centroid": [337.2, 476.0], "size": 71.0}, {"id": "r16", "number": 2, "path": "M130.5 417.2 L192.0 511.0 L96.0 511.0 Z", "centroid": [139.5, 479.7], "size": 67.1}, {"id": "r17", "number": 2, "path": "M81.3 424.1 L130.5 417.2 L96.0 511.0 Z", "centroid": [102.6, 450.8], "size": 46.8}, {"id": "r18", "number": 2, "path": "M170.7 355.7 L130.5 417.2 L76.4 331.3 Z", "centroid": [125.9, 368.1], "size": 58.2}, {"id": "r19", "number": 2, "path": "M130.5 417.2 L81.3 424.1 L76.4 331.3 Z", "centroid": [96.1, 390.9], "size": 48.0}, {"id": "r20", "number": 2, "path": "M169.4 46.7 L192.0 0.0 L249.6 18.2 Z", "centroid": [203.6, 21.7], "size": 39.4}, {"id": "r21", "number": 2, "path": "M164.3 101.4 L169.4 46.7 L249.6 18.2 Z", "centroid": [194.4, 55.5], "size": 46.0}, {"id": "r22", "number": 2, "path": "M169.4 46.7 L96.0 0.0 L192.0 0.0 Z", "centroid": [152.5, 15.6], "size": 47.4}, {"id": "r23", "number": 2, "path": "M0.0 192.0 L71.0 124.2 L31.4 208.9 Z", "centroid": [34.1, 175.0], "size": 40.8}, {"id": "r24", "number": 1, "path": "M71.0 124.2 L164.3 101.4 L177.9 152.4 Z", "centroid": [137.7, 126.0], "size": 50.3}, {"id": "r25", "number": 2, "path": "M306.4 20.2 L257.8 142.8 L249.6 18.2 Z", "centroid": [271.3, 60.4], "size": 59.4}, {"id": "r26", "number": 2, "path": "M511.0 192.0 L440.7 118.3 L511.0 96.0 Z", "centroid": [487.6, 135.4], "size": 58.1}, {"id": "r27", "number": 2, "path": "M460.9 35.4 L480.0 0.0 L511.0 0.0 Z", "centroid": [484.0, 11.8], "size": 23.4}, {"id": "r28", "number": 2, "path": "M480.0 0.0 L460.9 35.4 L384.0 0.0 Z", "centroid": [441.6, 11.8], "size": 41.2}, {"id": "r29", "number": 2, "path": "M451.7 237.8 L511.0 192.0 L511.0 288.0 Z", "centroid": [491.2, 239.3], "size": 53.3}, {"id": "r30", "number": 2, "path": "M460.3 324.3 L451.7 237.8 L511.0 288.0 Z", "centroid": [474.3, 283.4], "size": 48.4}, {"id": "r31", "number": 2, "path": "M451.7 237.8 L460.3 324.3 L366.0 312.8 Z", "centroid": [426.0, 291.7], "size": 63.4}, {"id": "r32", "number": 2, "path": "M480.0 511.0 L511.0 480.0 L511.0 511.0 Z", "centroid": [500.7, 500.7], "size": 21.9}, {"id": "r33", "number": 2, "path": "M261.3 442.4 L339.6 406.0 L288.0 511.0 Z", "centroid": [296.3, 453.1], "size": 56.3}, {"id": "r34", "number": 2, "path": "M192.0 511.0 L261.3 442.4 L288.0 511.0 Z", "centroid": [247.1, 488.1], "size": 57.4}, {"id": "r35", "number": 2, "path": "M261.3 442.4 L130.5 417.2 L170.7 355.7 Z", "centroid": [187.5, 405.1], "size": 67.3}, {"id": "r36", "number": 2, "path": "M130.5 417.2 L261.3 442.4 L192.0 511.0 Z", "centroid": [194.6, 456.9], "size": 73.2}, {"id": "r37", "number": 2, "path": "M339.6 406.0 L441.9 399.3 L384.0 511.0 Z", "centroid": [388.5, 438.8], "size": 74.3}, {"id": "r38", "number": 2, "path": "M511.0 480.0 L441.9 399.3 L511.0 384.0 Z", "centroid": [488.0, 421.1], "size": 57.6}, {"id": "r39", "number": 2, "path": "M441.9 399.3 L480.0 511.0 L384.0 511.0 Z", "centroid": [435.3, 473.8], "size": 73.2}, {"id": "r40", "number": 2, "path": "M480.0 511.0 L441.9 399.3 L511.0 480.0 Z", "centroid": [477.6, 463.4], "size": 48.2}, {"id": "r41", "number": 2, "path": "M441.9 399.3 L460.3 324.3 L511.0 384.0 Z", "centroid": [471.1, 369.2], "size": 49.5}, {"id": "r42", "number": 2, "path": "M460.3 324.3 L441.9 399.3 L366.0 312.8 Z", "centroid": [422.7, 345.5], "size": 60.3}, {"id": "r43", "number": 2, "path": "M441.9 399.3 L339.6 406.0 L366.0 312.8 Z", "centroid": [382.5, 372.7], "size": 68.4}, {"id": "r44", "number": 4, "path": "M71.0 124.2 L163.0 217.1 L31.4 208.9 Z", "centroid": [88.5, 183.4], "size": 75.7}, {"id": "r45", "number": 3, "path": "M163.0 217.1 L71.0 124.2 L177.9 152.4 Z", "centroid": [137.3, 164.5], "size": 60.5}, {"id": "r46", "number": 2, "path": "M257.8 142.8 L202.8 201.2 L177.9 152.4 Z", "centroid": [212.8, 165.5], "size": 45.5}, {"id": "r47", "number": 4, "path": "M202.8 201.2 L163.0 217.1 L177.9 152.4 Z", "centroid": [181.2, 190.2], "size": 34.2}, {"id": "r48", "number": 1, "path": "M163.0 217.1 L202.8 201.2 L183.3 232.1 Z", "centroid": [183.1, 216.8], "size": 21.5}, {"id": "r49", "number": 2, "path": "M298.6 204.8 L202.8 201.2 L257.8 142.8 Z", "centroid": [253.1, 182.9], "size": 53.8}, {"id": "r50", "number": 4, "path": "M202.8 201.2 L298.6 204.8 L234.1 274.3 Z", "centroid": [245.2, 226.8], "size": 58.7}, {"id": "r51", "number": 2, "path": "M96.0 0.0 L92.4 83.9 L64.8 29.4 Z", "centroid": [84.4, 37.8], "size": 35.4}, {"id": "r52", "number": 2, "path": "M169.4 46.7 L92.4 83.9 L96.0 0.0 Z", "centroid": [119.2, 43.6], "size": 56.3}, {"id": "r53", "number": 1, "path": "M71.0 124.2 L92.4 83.9 L164.3 101.4 Z", "centroid": [109.2, 103.2], "size": 40.4}, {"id": "r54", "number": 2, "path": "M306.4 20.2 L288.0 0.0 L384.0 0.0 Z", "centroid": [326.1, 6.7], "size": 31.2}, {"id": "r55", "number": 2, "path": "M192.0 0.0 L288.0 0.0 L249.6 18.2 Z", "centroid": [243.2, 6.1], "size": 29.6}, {"id": "r56", "number": 2, "path": "M288.0 0.0 L306.4 20.2 L249.6 18.2 Z", "centroid": [281.3, 12.8], "size": 23.6}, {"id": "r57", "number": 2, "path": "M306.4 20.2 L345.9 103.2 L257.8 142.8 Z", "centroid": [303.4, 88.7], "size": 66.6}, {"id": "r58", "number": 2, "path": "M345.9 103.2 L306.4 20.2 L384.0 0.0 Z", "centroid": [345.4, 41.2], "size": 60.2}, {"id": "r59", "number": 1, "path": "M440.7 118.3 L425.2 163.4 L410.6 143.6 Z", "centroid": [425.5, 141.8], "size": 22.0}, {"id": "r60", "number": 4, "path": "M425.2 163.4 L440.7 118.3 L511.0 192.0 Z", "centroid": [459.0, 157.9], "size": 46.4}, {"id": "r61", "number": 2, "path": "M451.7 237.8 L425.2 163.4 L511.0 192.0 Z", "centroid": [462.7, 197.7], "size": 53.1}, {"id": "r62", "number": 2, "path": "M437.1 105.4 L460.9 35.4 L511.0 96.0 Z", "centroid": [469.7, 78.9], "size": 49.8}, {"id": "r63", "number": 2, "path": "M460.9 35.4 L437.1 105.4 L384.0 0.0 Z", "centroid": [427.3, 46.9], "size": 55.8}, {"id": "r64", "number": 3, "path": "M437.1 105.4 L345.9 103.2 L384.0 0.0 Z", "centroid": [389.0, 69.5], "size": 68.9}, {"id": "r65", "number": 1, "path": "M437.1 105.4 L440.7 118.3 L410.6 143.6 Z", "centroid": [429.5, 122.5], "size": 15.5}, {"id": "r66", "number": 2, "path": "M349.7 226.2 L451.7 237.8 L366.0 312.8 Z", "centroid": [389.1, 259.0], "size": 65.8}, {"id": "r67", "number": 2, "path": "M261.3 442.4 L265.2 349.0 L339.6 406.0 Z", "centroid": [288.7, 399.1], "size": 59.9}, {"id": "r68", "number": 2, "path": "M339.6 406.0 L265.2 349.0 L366.0 312.8 Z", "centroid": [323.6, 355.9], "size": 64.9}, {"id": "r69", "number": 1, "path": "M162.4 229.6 L183.3 232.1 L164.9 255.5 Z", "centroid": [170.2, 239.1], "size": 16.4}, {"id": "r70", "number": 5, "path": "M162.4 229.6 L163.0 217.1 L183.3 232.1 Z", "centroid": [169.6, 226.3], "size": 11.5}, {"id": "r71", "number": 4, "path": "M162.4 229.6 L164.9 255.5 L31.4 208.9 Z", "centroid": [119.6, 231.3], "size": 40.9}, {"id": "r72", "number": 2, "path": "M163.0 217.1 L162.4 229.6 L31.4 208.9 Z", "centroid": [119.0, 218.5], "size": 28.7}, {"id": "r73", "number": 5, "path": "M217.8 267.5 L202.8 201.2 L234.1 274.3 Z", "centroid": [218.2, 247.7], "size": 22.1}, {"id": "r74", "number": 5, "path": "M202.8 201.2 L217.8 267.5 L183.3 232.1 Z", "centroid": [201.3, 233.6], "size": 29.6}, {"id": "r75", "number": 1, "path": "M183.3 232.1 L217.8 267.5 L164.9 255.5 Z", "centroid": [188.7, 251.7], "size": 27.0}, {"id": "r76", "number": 4, "path": "M164.9 255.5 L217.8 267.5 L170.7 355.7 Z", "centroid": [184.4, 292.9], "size": 51.2}, {"id": "r77", "number": 2, "path": "M254.4 322.3 L217.8 267.5 L234.1 274.3 Z", "centroid": [235.4, 288.1], "size": 18.0}, {"id": "r78", "number": 4, "path": "M153.4 87.2 L169.4 46.7 L164.3 101.4 Z", "centroid": [162.3, 78.5], "size": 18.3}, {"id": "r79", "number": 1, "path": "M92.4 83.9 L153.4 87.2 L164.3 101.4 Z", "centroid": [136.7, 90.9], "size": 20.3}, {"id": "r80", "number": 8, "path": "M153.4 87.2 L92.4 83.9 L169.4 46.7 Z", "centroid": [138.4, 72.6], "size": 35.5}, {"id": "r81", "number": 4, "path": "M28.1 110.7 L92.4 83.9 L71.0 124.2 Z", "centroid": [63.8, 106.3], "size": 31.7}, {"id": "r82", "number": 2, "path": "M0.0 96.0 L28.1 110.7 L0.0 192.0 Z", "centroid": [9.4, 132.9], "size": 36.7}, {"id": "r83", "number": 2, "path": "M28.1 110.7 L71.0 124.2 L0.0 192.0 Z", "centroid": [33.0, 142.3], "size": 44.0}, {"id": "r84", "number": 2, "path": "M28.1 110.7 L0.0 96.0 L64.8 29.4 Z", "centroid": [31.0, 78.7], "size": 37.6}, {"id": "r85", "number": 2, "path": "M92.4 83.9 L28.1 110.7 L64.8 29.4 Z", "centroid": [61.8, 74.7], "size": 46.0}, {"id": "r86", "number": 2, "path": "M348.2 134.0 L298.6 204.8 L257.8 142.8 Z", "centroid": [301.5, 160.5], "size": 54.6}, {"id": "r87", "number": 4, "path": "M440.7 118.3 L440.0 110.8 L511.0 96.0 Z", "centroid": [463.9, 108.4], "size": 16.5}, {"id": "r88", "number": 4, "path": "M440.0 110.8 L437.1 105.4 L511.0 96.0 Z", "centroid": [462.7, 104.1], "size": 14.6}, {"id": "r89", "number": 4, "path": "M265.2 349.0 L319.2 275.8 L366.0 312.8 Z", "centroid": [316.8, 312.6], "size": 52.1}, {"id": "r90", "number": 2, "path": "M319.2 275.8 L265.2 349.0 L254.4 322.3 Z", "centroid": [279.6, 315.7], "size": 33.4}, {"id": "r91", "number": 2, "path": "M319.2 275.8 L254.4 322.3 L234.1 274.3 Z", "centroid": [269.2, 290.8], "size": 45.0}, {"id": "r92", "number": 7, "path": "M298.6 204.8 L319.2 275.8 L234.1 274.3 Z", "centroid": [284.0, 251.7], "size": 54.8}, {"id": "r93", "number": 4, "path": "M390.0 174.5 L425.2 163.4 L451.7 237.8 Z", "centroid": [422.3, 191.9], "size": 38.2}, {"id": "r94", "number": 1, "path": "M425.2 163.4 L390.0 174.5 L410.6 143.6 Z", "centroid": [408.6, 160.5], "size": 20.7}, {"id": "r95", "number": 2, "path": "M239.6 349.1 L261.3 442.4 L170.7 355.7 Z", "centroid": [223.9, 382.4], "size": 57.3}, {"id": "r96", "number": 4, "path": "M217.8 267.5 L239.6 349.1 L170.7 355.7 Z", "centroid": [209.4, 324.1], "size": 53.7}, {"id": "r97", "number": 2, "path": "M239.6 349.1 L217.8 267.5 L254.4 322.3 Z", "centroid": [237.3, 313.0], "size": 29.9}, {"id": "r98", "number": 4, "path": "M345.9 103.2 L342.3 124.5 L257.8 142.8 Z", "centroid": [315.3, 123.5], "size": 29.4}, {"id": "r99", "number": 4, "path": "M342.3 124.5 L348.2 134.0 L257.8 142.8 Z", "centroid": [316.1, 133.7], "size": 21.3}, {"id": "r100", "number": 1, "path": "M360.3 127.6 L437.1 105.4 L410.6 143.6 Z", "centroid": [402.6, 125.5], "size": 34.3}, {"id": "r101", "number": 1, "path": "M437.1 105.4 L360.3 127.6 L345.9 103.2 Z", "centroid": [381.1, 112.1], "size": 33.1}, {"id": "r102", "number": 1, "path": "M390.0 174.5 L360.3 127.6 L410.6 143.6 Z", "centroid": [386.9, 148.6], "size": 30.7}, {"id": "r103", "number": 7, "path": "M360.3 127.6 L390.0 174.5 L348.2 134.0 Z", "centroid": [366.2, 145.3], "size": 19.4}, {"id": "r104", "number": 1, "path": "M360.3 127.6 L342.3 124.5 L345.9 103.2 Z", "centroid": [349.5, 118.4], "size": 14.0}, {"id": "r105", "number": 1, "path": "M342.3 124.5 L360.3 127.6 L348.2 134.0 Z", "centroid": [350.3, 128.7], "size": 8.7}, {"id": "r106", "number": 8, "path": "M324.0 275.3 L349.7 226.2 L366.0 312.8 Z", "centroid": [346.6, 271.4], "size": 38.9}, {"id": "r107", "number": 8, "path": "M319.2 275.8 L324.0 275.3 L366.0 312.8 Z", "centroid": [336.4, 288.0], "size": 10.1}, {"id": "r108", "number": 2, "path": "M349.7 226.2 L356.4 214.5 L451.7 237.8 Z", "centroid": [385.9, 226.2], "size": 25.3}, {"id": "r109", "number": 2, "path": "M356.4 214.5 L390.0 174.5 L451.7 237.8 Z", "centroid": [399.4, 208.9], "size": 47.9}, {"id": "r110", "number": 2, "path": "M390.0 174.5 L356.4 214.5 L348.2 134.0 Z", "centroid": [364.9, 174.3], "size": 38.9}, {"id": "r111", "number": 5, "path": "M356.4 214.5 L349.7 226.2 L298.6 204.8 Z", "centroid": [334.9, 215.2], "size": 19.3}, {"id": "r112", "number": 4, "path": "M348.2 134.0 L356.4 214.5 L298.6 204.8 Z", "centroid": [334.4, 184.4], "size": 47.8}, {"id": "r113", "number": 4, "path": "M261.2 349.9 L265.2 349.0 L261.3 442.4 Z", "centroid": [262.6, 380.4], "size": 13.6}, {"id": "r114", "number": 4, "path": "M239.6 349.1 L261.2 349.9 L261.3 442.4 Z", "centroid": [254.1, 380.5], "size": 31.6}, {"id": "r115", "number": 3, "path": "M265.2 349.0 L261.2 349.9 L254.4 322.3 Z", "centroid": [260.3, 340.4], "size": 7.6}, {"id": "r116", "number": 3, "path": "M261.2 349.9 L239.6 349.1 L254.4 322.3 Z", "centroid": [251.7, 340.4], "size": 17.2}, {"id": "r117", "number": 5, "path": "M324.0 275.3 L322.3 274.9 L349.7 226.2 Z", "centroid": [332.0, 258.8], "size": 6.9}, {"id": "r118", "number": 5, "path": "M349.7 226.2 L322.3 274.9 L298.6 204.8 Z", "centroid": [323.5, 235.3], "size": 39.2}, {"id": "r119", "number": 6, "path": "M322.3 274.9 L319.2 275.8 L298.6 204.8 Z", "centroid": [313.4, 251.8], "size": 10.9}], "freeform": true}